amt_tools/__init__.py
amt_tools/evaluate.py
amt_tools/inference.py
amt_tools/train.py
amt_tools/transcribe.py
amt_tools/datasets/GuitarSet.py
amt_tools/datasets/MAESTRO.py
amt_tools/datasets/MAPS.py
amt_tools/datasets/__init__.py
amt_tools/datasets/combo.py
amt_tools/datasets/common.py
amt_tools/features/__init__.py
amt_tools/features/combo.py
amt_tools/features/common.py
amt_tools/features/cqt.py
amt_tools/features/hcqt.py
amt_tools/features/hvqt.py
amt_tools/features/mel.py
amt_tools/features/power.py
amt_tools/features/stft.py
amt_tools/features/stream.py
amt_tools/features/vqt.py
amt_tools/features/waveform.py
amt_tools/models/__init__.py
amt_tools/models/common.py
amt_tools/models/onsetsframes.py
amt_tools/models/tabcnn.py
amt_tools/tools/__init__.py
amt_tools/tools/constants.py
amt_tools/tools/instrument.py
amt_tools/tools/io.py
amt_tools/tools/utils.py
amt_tools/tools/visualize.py
amt_tools-0.3.2.dist-info/LICENSE.txt
amt_tools-0.3.2.dist-info/METADATA
amt_tools-0.3.2.dist-info/WHEEL
amt_tools-0.3.2.dist-info/top_level.txt
amt_tools-0.3.2.dist-info/RECORD
