Metadata-Version: 2.1
Name: amt-tools
Version: 0.3.2
Summary: Machine learning tools and framework for automatic music transcription
Home-page: https://github.com/cwitkowitz/amt-tools
Author: Frank Cwitkowitz
Author-email: fcwitkow@ur.rochester.edu
License: MIT
Requires-Python: >=3.8
License-File: LICENSE.txt
Requires-Dist: numpy
Requires-Dist: librosa
Requires-Dist: torch
Requires-Dist: matplotlib
Requires-Dist: sacred
Requires-Dist: mir-eval
Requires-Dist: jams
Requires-Dist: mido
Requires-Dist: requests
Requires-Dist: tqdm
Requires-Dist: tensorboard
Requires-Dist: tensorboardX
Requires-Dist: scipy
Requires-Dist: pandas
Requires-Dist: mirdata
Requires-Dist: sounddevice
Requires-Dist: pynput
